rutimeparser-1.1.1.dist-info/dependency_links.txt
rutimeparser-1.1.1.dist-info/entry_points.txt
rutimeparser-1.1.1.dist-info/METADATA
rutimeparser-1.1.1.dist-info/top_level.txt
rutimeparser-1.1.1.dist-info/WHEEL
rutimeparser/get_words.py
rutimeparser/core.py
rutimeparser/__init__.py
rutimeparser/reducers.py
rutimeparser/utils.py
rutimeparser/numbers.py
rutimeparser/get_cat.py
rutimeparser/rules.py
rutimeparser/shortcuts.py
rutimeparser-1.1.1.dist-info/LICENSE
rutimeparser-1.1.1.dist-info/RECORD