Metadata-Version: 2.1
Name: rutimeparser
Version: 1.1.1
Summary: Recognize date and time in russian text.
Home-Page: https://github.com/orsinium/rutimeparser
Author: Gram (@orsinium)
Author-email: master_fess@mail.ru
Requires-Python: >=2.7
Classifier: Development Status :: 5 - Production/Stable
Classifier: Intended Audience :: Developers
Classifier: License :: OSI Approved :: MIT License
Classifier: Programming Language :: Python :: 2.7
Classifier: Programming Language :: Python :: 2
Classifier: Programming Language :: Python :: 3.5
Classifier: Programming Language :: Python :: 3.6
Classifier: Programming Language :: Python :: 3.7
Classifier: Programming Language :: Python :: 3
Classifier: Programming Language :: Python
Classifier: Topic :: Software Development :: Libraries :: Python Modules
Requires-Dist: pytz
